chamois/__init__.py
chamois/embeddings/__init__.py
chamois/embeddings/_embed.py
chamois/embeddings/_protocols.py
chamois/embeddings/embedding.py
chamois/embeddings/_providers/openai.py
chamois-0.0.1.dist-info/METADATA
chamois-0.0.1.dist-info/WHEEL
chamois-0.0.1.dist-info/licenses/LICENSE
chamois-0.0.1.dist-info/RECORD
