Metadata-Version: 2.4
Name: chamois
Version: 0.0.1
Summary: The standardized information retrieval interface.
Author-email: William Bakst <william@mirascope.com>
Maintainer-email: William Bakst <william@mirascope.com>
License-File: LICENSE
Keywords: artificial intelligence,developer tools,embeddings,llm,rag
Classifier: Development Status :: 3 - Alpha
Classifier: Intended Audience :: Developers
Classifier: License :: OSI Approved :: MIT License
Classifier: Programming Language :: Python :: 3
Classifier: Programming Language :: Python :: 3.10
Classifier: Programming Language :: Python :: 3.11
Classifier: Programming Language :: Python :: 3.12
Classifier: Programming Language :: Python :: 3.13
Classifier: Topic :: Scientific/Engineering :: Artificial Intelligence
Classifier: Topic :: Software Development :: Libraries
Requires-Python: >=3.10
Requires-Dist: typing-extensions>=4.12.2
Provides-Extra: openai
Requires-Dist: openai>=1.66.5; extra == 'openai'
